indico_owncloud/__init__.py
indico_owncloud/blueprint.py
indico_owncloud/controllers.py
indico_owncloud/forms.py
indico_owncloud/plugin.py
indico_owncloud/util.py
indico_owncloud/static/dist/manifest.json
indico_owncloud/static/dist/css/main.ade64bf5.css
indico_owncloud/static/dist/css/main.ade64bf5.css.map
indico_owncloud/static/dist/js/main.ba3cccf2.bundle.js
indico_owncloud/static/dist/js/monaco.css.worker.js
indico_owncloud/static/dist/js/monaco.css.worker.js.map
indico_owncloud/static/dist/js/monaco.editor.worker.js
indico_owncloud/static/dist/js/monaco.editor.worker.js.map
indico_owncloud/static/dist/js/monaco.html.worker.js
indico_owncloud/static/dist/js/monaco.html.worker.js.map
indico_owncloud/static/dist/js/owncloud.8a1e77e3.bundle.js
indico_owncloud/static/dist/js/owncloud.8a1e77e3.bundle.js.map
indico_owncloud/templates/add_owncloud_files.html
indico_owncloud/templates/owncloud_button.html
indico_owncloud/templates/owncloud_filepicker_widget.html
indico_owncloud/translations/messages.pot
indico_owncloud/translations/cs_CZ/LC_MESSAGES/messages.mo
indico_owncloud/translations/cs_CZ/LC_MESSAGES/messages.po
indico_owncloud/translations/de_DE/LC_MESSAGES/messages.mo
indico_owncloud/translations/de_DE/LC_MESSAGES/messages.po
indico_owncloud/translations/en_CA/LC_MESSAGES/messages.mo
indico_owncloud/translations/en_CA/LC_MESSAGES/messages.po
indico_owncloud/translations/en_GB/LC_MESSAGES/messages.mo
indico_owncloud/translations/en_GB/LC_MESSAGES/messages.po
indico_owncloud/translations/es_ES/LC_MESSAGES/messages.mo
indico_owncloud/translations/es_ES/LC_MESSAGES/messages.po
indico_owncloud/translations/fr_FR/LC_MESSAGES/messages.mo
indico_owncloud/translations/fr_FR/LC_MESSAGES/messages.po
indico_owncloud/translations/hu_HU/LC_MESSAGES/messages.mo
indico_owncloud/translations/hu_HU/LC_MESSAGES/messages.po
indico_owncloud/translations/it_IT/LC_MESSAGES/messages.mo
indico_owncloud/translations/it_IT/LC_MESSAGES/messages.po
indico_plugin_owncloud-3.3.3.dist-info/METADATA
indico_plugin_owncloud-3.3.3.dist-info/WHEEL
indico_plugin_owncloud-3.3.3.dist-info/entry_points.txt
indico_plugin_owncloud-3.3.3.dist-info/RECORD
